bin_maker/__init__.py
bin_maker/action.py
bin_maker/build.py
bin_maker-3.1.0.dist-info/LICENSE
bin_maker-3.1.0.dist-info/METADATA
bin_maker-3.1.0.dist-info/WHEEL
bin_maker-3.1.0.dist-info/entry_points.txt
bin_maker-3.1.0.dist-info/top_level.txt
bin_maker-3.1.0.dist-info/RECORD
