Metadata-Version: 2.1
Name: bin-maker
Version: 3.1.0
Summary: protect and speed up python source code
Home-page: UNKNOWN
Author: etherfurnace
Author-email: core@etherfurnace.com
License: UNKNOWN
Platform: UNKNOWN
License-File: LICENSE
Requires-Dist: cython (==0.29.21)
Requires-Dist: PyInstaller (==4.0)
